pgzhelper/__init__.py
pgzhelper/pgzhelper.py
pgzhelper_rw-1.0.10.dist-info/LICENSE
pgzhelper_rw-1.0.10.dist-info/METADATA
pgzhelper_rw-1.0.10.dist-info/WHEEL
pgzhelper_rw-1.0.10.dist-info/top_level.txt
pgzhelper_rw-1.0.10.dist-info/RECORD
