Metadata-Version: 2.1
Name: pgzhelper-rw
Version: 1.0.10
Summary: Pygame Zero Helper enhance Pygame Zero with additional capabilities
Home-page: https://github.com/roboticsware/pgzhelper/
Download-URL: https://github.com/roboticsware/pgzhelper/archive/refs/heads/master.zip
Author: Cort + Roboticsware
Author-email: roboticsware.uz@gmail.com
Keywords: roboticsware,neopia,pygame zero
Classifier: Development Status :: 5 - Production/Stable
Classifier: Intended Audience :: Education
Classifier: License :: OSI Approved :: GNU Lesser General Public License v3 (LGPLv3)
Classifier: Programming Language :: Python :: 3 :: Only
Classifier: Topic :: Education
Classifier: Topic :: Games/Entertainment
Requires-Python: >=3.7
License-File: LICENSE
Requires-Dist: pgzero (>=1.2)
